qytorch/__init__.py
qytorch/a.py
qytorch/qconv.py
qytorch/qlinear.py
qytorch/qmha.py
qytorch/qtransformer.py
qytorch/quat_base.py
qytorch-0.0.3.dist-info/LICENSE
qytorch-0.0.3.dist-info/METADATA
qytorch-0.0.3.dist-info/WHEEL
qytorch-0.0.3.dist-info/top_level.txt
qytorch-0.0.3.dist-info/RECORD
